Palmto_gen/__init__.py
Palmto_gen/data/porto.geojson
Palmto_gen/data/porto_sample_data.pkl
palmto_gen-0.3.2.dist-info/licenses/LICENSE.txt
palmto_gen-0.3.2.dist-info/METADATA
palmto_gen-0.3.2.dist-info/WHEEL
palmto_gen-0.3.2.dist-info/top_level.txt
palmto_gen-0.3.2.dist-info/RECORD
