Metadata-Version: 2.4
Name: Palmto_gen
Version: 0.3.2
Summary: Generate synthetic trajectories using PLMs
Home-page: 
Author: Hayat Sultan, Joey Cherisea
Author-email: hayatsul@ualberta.ca, hai.p@northeastern.edu
License: MIT
Project-URL: Documentation, https://palmto-gen.readthedocs.io/en/latest/
Project-URL: Source, https://github.com/HayatSultan/PaLMTo-Gen
Project-URL: Bug Reports, https://github.com/HayatSultan/PaLMTo-Gen/issues
Keywords: trajectory generationProbablistic Language Models
Classifier: Development Status :: 4 - Beta
Classifier: Intended Audience :: Education
Classifier: Operating System :: Microsoft :: Windows :: Windows 10
Classifier: License :: OSI Approved :: MIT License
Classifier: Programming Language :: Python :: 3
License-File: LICENSE.txt
Requires-Dist: geopandas
Requires-Dist: tqdm
Requires-Dist: geopy
Requires-Dist: scipy
Requires-Dist: folium
Dynamic: author
Dynamic: author-email
Dynamic: classifier
Dynamic: description
Dynamic: description-content-type
Dynamic: keywords
Dynamic: license
Dynamic: license-file
Dynamic: project-url
Dynamic: requires-dist
Dynamic: summary
